pysdn/__init__.py
pysdn/cli.py
pysdn/pysdn.py
pysdn-0.1.0.dist-info/LICENSE
pysdn-0.1.0.dist-info/METADATA
pysdn-0.1.0.dist-info/WHEEL
pysdn-0.1.0.dist-info/entry_points.txt
pysdn-0.1.0.dist-info/top_level.txt
pysdn-0.1.0.dist-info/RECORD
