Metadata-Version: 2.1
Name: pysdn
Version: 0.1.0
Summary: Python / CFFI-based glue library to access Linux XDP/eBPF, bpfilter, tc and Facebook Katran
Home-page: https://github.com/crossbario/pysdn
Author: Crossbar.io Technologies GmbH
Author-email: contact@crossbario.com
License: MIT license
Keywords: pysdn
Platform: UNKNOWN
Classifier: Development Status :: 2 - Pre-Alpha
Classifier: Intended Audience :: Developers
Classifier: License :: OSI Approved :: MIT License
Classifier: Natural Language :: English
Classifier: Programming Language :: Python :: 2
Classifier: Programming Language :: Python :: 2.7
Classifier: Programming Language :: Python :: 3
Classifier: Programming Language :: Python :: 3.5
Classifier: Programming Language :: Python :: 3.6
Classifier: Programming Language :: Python :: 3.7
Classifier: Programming Language :: Python :: 3.8
Requires-Python: >=2.7, !=3.0.*, !=3.1.*, !=3.2.*, !=3.3.*, !=3.4.*
Requires-Dist: Click (>=7.0)
